add_on_class/__init__.py
add_on_class/add_on_class.py
add_on_class-0.1.3.dist-info/LICENSE
add_on_class-0.1.3.dist-info/METADATA
add_on_class-0.1.3.dist-info/WHEEL
add_on_class-0.1.3.dist-info/top_level.txt
add_on_class-0.1.3.dist-info/RECORD
