Metadata-Version: 2.1
Name: add-on-class
Version: 0.1.3
Summary: This package provides you with a module that allows you to easily define classes that are stacked on top of each other and add features to each other, creating a whole new class.
Home-page: https://github.com/BehzadShayegh/add-on-class
Author: Behzad Shayegh
Author-email: behzad.shayegh@ut.ac.ir
License: UNKNOWN
Project-URL: Bug Tracker, https://github.com/BehzadShayegh/add-on-class/issues
Platform: UNKNOWN
Classifier: Programming Language :: Python :: 3
Classifier: License :: OSI Approved :: MIT License
Classifier: Operating System :: OS Independent
Requires-Python: >=3.6
License-File: LICENSE
